Metadata-Version: 2.1
Name: odoo14-addon-l10n-ro-account-bank-statement-import-mt940-base
Version: 14.0.1.5.0
Summary: Romania - MT940 Bank Statements Import
Home-page: https://github.com/OCA/l10n-romania
Author: NextERP Romania,Odoo Community Association (OCA),Therp BV
Author-email: support@odoo-community.org
License: AGPL-3
Platform: UNKNOWN
Classifier: Programming Language :: Python
Classifier: Framework :: Odoo
Classifier: Framework :: Odoo :: 14.0
Classifier: License :: OSI Approved :: GNU Affero General Public License v3
Classifier: Development Status :: 6 - Mature
Requires-Python: >=3.6
Requires-Dist: odoo14-addon-account-statement-import
Requires-Dist: odoo14-addon-l10n-ro-config
Requires-Dist: odoo <14.1dev,>=14.0a
